fdate/__init__.py
fdate/fdate.py
fdate-0.1.7.dist-info/DESCRIPTION.rst
fdate-0.1.7.dist-info/METADATA
fdate-0.1.7.dist-info/RECORD
fdate-0.1.7.dist-info/WHEEL
fdate-0.1.7.dist-info/metadata.json
fdate-0.1.7.dist-info/top_level.txt
