Metadata-Version: 2.0
Name: fdate
Version: 0.1.7
Summary: Formats date string as 'yyyy-mm-dd' and manipulates dates.
Home-page: https://github.com/nullgo/fdate
Author: qx3501332
Author-email: x.qiu@qq.com
License: MIT License
Platform: UNKNOWN
Classifier: Development Status :: 4 - Beta
Classifier: Intended Audience :: Developers
Classifier: Operating System :: OS Independent
Classifier: Programming Language :: Python :: 3.6
Classifier: Topic :: Software Development :: Libraries :: Python Modules
